LTPpyTools/__init__.py
LTPpyTools/console.py
LTPpyTools/flush.py
LTPpyTools/log.py
LTPpyTools/music.py
LTPpyTools/option.py
ltppytools-0.4.0.dist-info/licenses/LICENSE.txt
ltppytools-0.4.0.dist-info/METADATA
ltppytools-0.4.0.dist-info/WHEEL
ltppytools-0.4.0.dist-info/top_level.txt
ltppytools-0.4.0.dist-info/RECORD
