Metadata-Version: 2.4
Name: LTPpyTools
Version: 0.4.0
Summary: A python package for any python program develop.
Home-page: https://github.com/LightingXT/Tools?tab=MIT-1-ov-file
Author: LTPLAX
Author-email: no@no.com
Classifier: Programming Language :: Python :: 3
Classifier: License :: OSI Approved :: MIT License
Classifier: Operating System :: OS Independent
Requires-Python: >=3.8
License-File: LICENSE.txt
Dynamic: author
Dynamic: author-email
Dynamic: classifier
Dynamic: description
Dynamic: description-content-type
Dynamic: home-page
Dynamic: license-file
Dynamic: requires-python
Dynamic: summary
